{
  "version": "3.0",
  "updated": "2026-04-15T23:52:21.366397+09:00",
  "updated_display": "2026. 04. 15. PM 11:52:21",
  "count": 17,
  "total": 17,
  "weights": {
    "momentum": 0.25,
    "fundamental": 0.55,
    "valuation": 0.2
  },
  "data": [
    {
      "ticker": "NVDA",
      "error": false,
      "scores": {
        "momentum": 0.27,
        "fundamental": 0.71,
        "valuation": 0.23,
        "risk": -0.5,
        "final": 0.51
      },
      "raw": {
        "price": 199.4099,
        "sma200": 181.12434,
        "52w_change": 0,
        "5d_change": 0.0843,
        "rsi": 70.1,
        "macd_cross": 1.0,
        "eps_growth": 0.945,
        "revenue_growth": 0.732,
        "profit_margin": 0.55603004,
        "roe": 1.01485,
        "fcf_margin": 0.2691929929187143,
        "pe": 40.77912,
        "forward_pe": 17.885963,
        "peg": 2,
        "beta": 2.335
      },
      "rank": 1
    },
    {
      "ticker": "MSFT",
      "error": false,
      "scores": {
        "momentum": 0.47,
        "fundamental": -0.06,
        "valuation": 0.93,
        "risk": 0.5,
        "final": 0.27
      },
      "raw": {
        "price": 406.5445,
        "sma200": 473.1121,
        "52w_change": 0,
        "5d_change": 0.0897,
        "rsi": 65.8,
        "macd_cross": 1.0,
        "eps_growth": 0.595,
        "revenue_growth": 0.167,
        "profit_margin": 0.39044,
        "roe": 0.34390998,
        "fcf_margin": 0.17561007740445236,
        "pe": 25.40903,
        "forward_pe": 21.50559,
        "peg": 1.2478,
        "beta": 1.107
      },
      "rank": 2
    },
    {
      "ticker": "V",
      "error": false,
      "scores": {
        "momentum": 0.12,
        "fundamental": 0.13,
        "valuation": 0.22,
        "risk": 0.5,
        "final": 0.14
      },
      "raw": {
        "price": 312.64,
        "sma200": 335.10574,
        "52w_change": 0,
        "5d_change": 0.0141,
        "rsi": 56.6,
        "macd_cross": 1.0,
        "eps_growth": 0.143,
        "revenue_growth": 0.146,
        "profit_margin": 0.50233,
        "roe": 0.53954,
        "fcf_margin": 0.5322956688247912,
        "pe": 29.355871,
        "forward_pe": 21.497097,
        "peg": 2,
        "beta": 0.799
      },
      "rank": 3
    },
    {
      "ticker": "AAPL",
      "error": false,
      "scores": {
        "momentum": 0.08,
        "fundamental": 0.07,
        "valuation": 0.17,
        "risk": 0.5,
        "final": 0.09
      },
      "raw": {
        "price": 261.745,
        "sma200": 251.2118,
        "52w_change": 0,
        "5d_change": 0.0048,
        "rsi": 56.6,
        "macd_cross": 1.0,
        "eps_growth": 0.159,
        "revenue_growth": 0.157,
        "profit_margin": 0.27037,
        "roe": 1.5202099,
        "fcf_margin": 0.2440509709059201,
        "pe": 33.17427,
        "forward_pe": 28.10766,
        "peg": 2,
        "beta": 1.109
      },
      "rank": 4
    },
    {
      "ticker": "TSM",
      "error": false,
      "scores": {
        "momentum": 0.28,
        "fundamental": -0.07,
        "valuation": 0.22,
        "risk": 0.5,
        "final": 0.07
      },
      "raw": {
        "price": 380.8646,
        "sma200": 295.4742,
        "52w_change": 0,
        "5d_change": 0.0422,
        "rsi": 66.4,
        "macd_cross": 1.0,
        "eps_growth": 0.35,
        "revenue_growth": 0.205,
        "profit_margin": 0.45099998,
        "roe": 0.35064,
        "fcf_margin": 0.16892625861565028,
        "pe": 36.58642,
        "forward_pe": 20.66122,
        "peg": 2,
        "beta": 1.251
      },
      "rank": 5
    },
    {
      "ticker": "LLY",
      "error": false,
      "scores": {
        "momentum": -0.18,
        "fundamental": 0.09,
        "valuation": 0.21,
        "risk": 0.5,
        "final": 0.05
      },
      "raw": {
        "price": 915.485,
        "sma200": 903.3358,
        "52w_change": 0,
        "5d_change": -0.0416,
        "rsi": 42.4,
        "macd_cross": 1.0,
        "eps_growth": 0.505,
        "revenue_growth": 0.426,
        "profit_margin": 0.31667,
        "roe": 1.01159,
        "fcf_margin": 0.02993295446533058,
        "pe": 39.855682,
        "forward_pe": 21.788597,
        "peg": 2,
        "beta": 0.504
      },
      "rank": 6
    },
    {
      "ticker": "GOOGL",
      "error": false,
      "scores": {
        "momentum": 0.32,
        "fundamental": -0.23,
        "valuation": 0.2,
        "risk": 0.5,
        "final": -0.01
      },
      "raw": {
        "price": 334.14,
        "sma200": 270.0988,
        "52w_change": 0,
        "5d_change": 0.0491,
        "rsi": 69.7,
        "macd_cross": 1.0,
        "eps_growth": 0.298,
        "revenue_growth": 0.18,
        "profit_margin": 0.32810003,
        "roe": 0.35705003,
        "fcf_margin": 0.09455057798872078,
        "pe": 30.881702,
        "forward_pe": 24.85521,
        "peg": 2,
        "beta": 1.128
      },
      "rank": 7
    },
    {
      "ticker": "META",
      "error": false,
      "scores": {
        "momentum": 0.41,
        "fundamental": -0.29,
        "valuation": 0.24,
        "risk": 0.5,
        "final": -0.01
      },
      "raw": {
        "price": 674.431,
        "sma200": 682.0254,
        "52w_change": 0,
        "5d_change": 0.0733,
        "rsi": 67.3,
        "macd_cross": 1.0,
        "eps_growth": 0.093,
        "revenue_growth": 0.238,
        "profit_margin": 0.30084,
        "roe": 0.30238,
        "fcf_margin": 0.11659870164587598,
        "pe": 28.674788,
        "forward_pe": 18.93601,
        "peg": 2,
        "beta": 1.309
      },
      "rank": 8
    },
    {
      "ticker": "ASML",
      "error": false,
      "scores": {
        "momentum": 0.07,
        "fundamental": -0.23,
        "valuation": 0.12,
        "risk": 0.5,
        "final": -0.09
      },
      "raw": {
        "price": 1451.135,
        "sma200": 1074.5677,
        "52w_change": 0,
        "5d_change": 0.0022,
        "rsi": 56.3,
        "macd_cross": 1.0,
        "eps_growth": 0.054,
        "revenue_growth": 0.049,
        "profit_margin": 0.29416,
        "roe": 0.50458,
        "fcf_margin": 0.3322875674808145,
        "pe": 50.299305,
        "forward_pe": 31.769482,
        "peg": 2,
        "beta": 1.382
      },
      "rank": 9
    },
    {
      "ticker": "GE",
      "error": false,
      "scores": {
        "momentum": 0.07,
        "fundamental": -0.29,
        "valuation": 0.11,
        "risk": 0.5,
        "final": -0.12
      },
      "raw": {
        "price": 313.915,
        "sma200": 295.7992,
        "52w_change": 0,
        "5d_change": 0.0029,
        "rsi": 56.5,
        "macd_cross": 1.0,
        "eps_growth": 0.338,
        "revenue_growth": 0.176,
        "profit_margin": 0.18982,
        "roe": 0.44692,
        "fcf_margin": 0.11364082379847983,
        "pe": 38.99565,
        "forward_pe": 36.437553,
        "peg": 2,
        "beta": 1.428
      },
      "rank": 10
    },
    {
      "ticker": "JPM",
      "error": false,
      "scores": {
        "momentum": 0.02,
        "fundamental": -0.41,
        "valuation": 0.3,
        "risk": 0.5,
        "final": -0.16
      },
      "raw": {
        "price": 306.09,
        "sma200": 303.37234,
        "52w_change": 0,
        "5d_change": -0.0137,
        "rsi": 59.1,
        "macd_cross": 1.0,
        "eps_growth": 0.126,
        "revenue_growth": 0.127,
        "profit_margin": 0.33936,
        "roe": 0.16465001,
        "fcf_margin": 0.0,
        "pe": 14.659483,
        "forward_pe": 13.057577,
        "peg": 2,
        "beta": 1.043
      },
      "rank": 11
    },
    {
      "ticker": "AMZN",
      "error": false,
      "scores": {
        "momentum": 0.17,
        "fundamental": -0.57,
        "valuation": 0.18,
        "risk": 0.5,
        "final": -0.23
      },
      "raw": {
        "price": 248.07,
        "sma200": 225.15645,
        "52w_change": 0,
        "5d_change": 0.0617,
        "rsi": 75.3,
        "macd_cross": 1.0,
        "eps_growth": 0.059,
        "revenue_growth": 0.136,
        "profit_margin": 0.108339995,
        "roe": 0.22286,
        "fcf_margin": 0.0331877933663955,
        "pe": 34.598328,
        "forward_pe": 26.433903,
        "peg": 2,
        "beta": 1.383
      },
      "rank": 12
    },
    {
      "ticker": "CAT",
      "error": false,
      "scores": {
        "momentum": 0.02,
        "fundamental": -0.51,
        "valuation": 0.16,
        "risk": -0.5,
        "final": -0.24
      },
      "raw": {
        "price": 775.39,
        "sma200": 563.71967,
        "52w_change": 0,
        "5d_change": -0.0148,
        "rsi": 61.0,
        "macd_cross": 1.0,
        "eps_growth": -0.139,
        "revenue_growth": 0.18,
        "profit_margin": 0.13144,
        "roe": 0.43526,
        "fcf_margin": 0.08638609985285331,
        "pe": 41.20032,
        "forward_pe": 27.872658,
        "peg": 2,
        "beta": 1.519
      },
      "rank": 13
    },
    {
      "ticker": "COST",
      "error": false,
      "scores": {
        "momentum": -0.44,
        "fundamental": -0.45,
        "valuation": 0.05,
        "risk": 0.5,
        "final": -0.35
      },
      "raw": {
        "price": 974.04,
        "sma200": 949.0998,
        "52w_change": 0,
        "5d_change": -0.0562,
        "rsi": 41.8,
        "macd_cross": -1.0,
        "eps_growth": 0.456,
        "revenue_growth": 0.215,
        "profit_margin": 0.029860001,
        "roe": 0.29650998,
        "fcf_margin": 0.023371263642362767,
        "pe": 50.731247,
        "forward_pe": 43.35593,
        "peg": 2,
        "beta": 0.978
      },
      "rank": 14
    },
    {
      "ticker": "WMT",
      "error": false,
      "scores": {
        "momentum": -0.14,
        "fundamental": -0.77,
        "valuation": 0.09,
        "risk": 0.5,
        "final": -0.44
      },
      "raw": {
        "price": 123.9809,
        "sma200": 110.2989,
        "52w_change": 0,
        "5d_change": -0.0399,
        "rsi": 48.6,
        "macd_cross": 1.0,
        "eps_growth": -0.194,
        "revenue_growth": 0.056,
        "profit_margin": 0.0307,
        "roe": 0.21847,
        "fcf_margin": 0.014799211443498826,
        "pe": 45.41425,
        "forward_pe": 37.744625,
        "peg": 2,
        "beta": 0.661
      },
      "rank": 15
    },
    {
      "ticker": "XOM",
      "error": false,
      "scores": {
        "momentum": -0.42,
        "fundamental": -0.76,
        "valuation": 0.28,
        "risk": -0.3,
        "final": -0.47
      },
      "raw": {
        "price": 148.2401,
        "sma200": 125.3556,
        "52w_change": 0,
        "5d_change": -0.0439,
        "rsi": 36.6,
        "macd_cross": -1.0,
        "eps_growth": -0.146,
        "revenue_growth": -0.013,
        "profit_margin": 0.089049995,
        "roe": 0.110810004,
        "fcf_margin": 0.03775721256665287,
        "pe": 22.12539,
        "forward_pe": 14.894685,
        "peg": 2,
        "beta": 0.288
      },
      "rank": 16
    },
    {
      "ticker": "TSLA",
      "error": false,
      "scores": {
        "momentum": 0.41,
        "fundamental": -0.97,
        "valuation": -1.0,
        "risk": -0.5,
        "final": -0.63
      },
      "raw": {
        "price": 377.685,
        "sma200": 397.67004,
        "52w_change": 0,
        "5d_change": 0.0928,
        "rsi": 52.3,
        "macd_cross": 1.0,
        "eps_growth": -0.605,
        "revenue_growth": -0.031,
        "profit_margin": 0.040009998,
        "roe": 0.049250003,
        "fcf_margin": 0.03936246788708833,
        "pe": 346.5,
        "forward_pe": 136.25983,
        "peg": 2,
        "beta": 1.915
      },
      "rank": 17
    }
  ]
}